LICENSE
MANIFEST.in
README.rst
VERSION
setup.py
piwik/__init__.py
piwik/api.py
piwik.egg-info/PKG-INFO
piwik.egg-info/SOURCES.txt
piwik.egg-info/dependency_links.txt
piwik.egg-info/requires.txt
piwik.egg-info/top_level.txt
piwik/django/__init__.py
piwik/django/admin.py
piwik/django/middleware.py
piwik/django/models.py
piwik/django/processors.py
piwik/django/tests.py
piwik/django/templates/admin/piwik/stats.html
piwik/django/templates/admin/piwik/table.html
piwik/django/templatetags/__init__.py
piwik/django/templatetags/piwik_json_tables.py