Metadata-Version: 1.0
Name: piwik
Version: 0.5.1
Summary: Access Piwik in python
Home-page: http://forge.2metz.fr/p/python-piwik/
Author: François de Metz
Author-email: francois@2metz.fr
License: BSD
Platform: UNKNOWN
Classifier: Development Status :: 4 - Beta
Classifier: Environment :: Web Environment
Classifier: Framework :: Django
Classifier: Operating System :: OS Independent
Classifier: Topic :: Internet :: Log Analysis
Classifier: License :: OSI Approved :: BSD License
Classifier: Programming Language :: Python
